README.md
setup.py
sinara_stabilizer.egg-info/PKG-INFO
sinara_stabilizer.egg-info/SOURCES.txt
sinara_stabilizer.egg-info/dependency_links.txt
sinara_stabilizer.egg-info/requires.txt
sinara_stabilizer.egg-info/top_level.txt
stabilizer/__init__.py
stabilizer/iir_coefficients.py
stabilizer/stream.py
stabilizer/telemetry.py