Metadata-Version: 2.1
Name: sinara-stabilizer
Version: 0.7.0
Summary: Stabilizer Utilities
Home-page: UNKNOWN
Author: QUARTIQ GmbH
License: MIT
Platform: UNKNOWN
